{"trades": [{"id": "b3bb71cc-3db1-48ee-ac30-923b7039aed8", "strategy_name": "AlligatorV2", "symbol": "ETC-USDT", "exchange": "Bybit Spot", "type": "long", "entry_price": 18.42, "exit_price": 18.85446713746095, "qty": 228.06406203, "fee": 8.500966385373092, "size": 4200.9400225926, "PNL": 90.58537380251732, "PNL_percentage": 2.156311999584626, "holding_period": 8280.0, "opened_at": 1746766800000.0, "closed_at": 1746775080000.0}, {"id": "94b27675-0976-4423-847d-0a4d7944f9ef", "strategy_name": "AlligatorV2", "symbol": "ETC-USDT", "exchange": "Bybit Spot", "type": "long", "entry_price": 19.16, "exit_price": 19.770070488882915, "qty": 163.88758368, "fee": 6.380155184915098, "size": 3140.0861033088, "PNL": 93.60282311258214, "PNL_percentage": 2.980899887233988, "holding_period": 103200.0, "opened_at": 1746792000000.0, "closed_at": 1746895200000.0}, {"id": "d78c949a-fbd1-4fe8-995b-875dea6e9d16", "strategy_name": "AlligatorV2", "symbol": "ETC-USDT", "exchange": "Bybit Spot", "type": "long", "entry_price": 20.29, "exit_price": 19.45245815949936, "qty": 167.528647, "fee": 6.658000243915039, "size": 3399.15624763, "PNL": -146.97025158887672, "PNL_percentage": -4.32372744534321, "holding_period": 138540.0, "opened_at": 1746936000000.0, "closed_at": 1747074540000.0}, {"id": "e0d74fe8-2665-4d50-a81e-183ba8e0da57", "strategy_name": "AlligatorV2", "symbol": "ETC-USDT", "exchange": "Bybit Spot", "type": "long", "entry_price": 17.64, "exit_price": 17.91799759147901, "qty": 357.75361743, "fee": 12.721002266918843, "size": 6310.7738114652, "PNL": 86.73364172152459, "PNL_percentage": 1.3743741150086832, "holding_period": 42840.0, "opened_at": 1752127200000.0, "closed_at": 1752170040000.0}, {"id": "3dd2a51e-d50a-4d61-86c1-006cd1038efc", "strategy_name": "AlligatorV2", "symbol": "ETC-USDT", "exchange": "Bybit Spot", "type": "long", "entry_price": 18.61, "exit_price": 18.102548513565885, "qty": 274.86967343, "fee": 10.091166220706885, "size": 5115.324622532299, "PNL": -149.57419057841986, "PNL_percentage": -2.9240410260487906, "holding_period": 48360.0, "opened_at": 1752224400000.0, "closed_at": 1752272760000.0}, {"id": "2b9670bd-d832-450b-ac19-9e2f5e43604d", "strategy_name": "AlligatorV2", "symbol": "ETC-USDT", "exchange": "Bybit Spot", "type": "long", "entry_price": 23.46, "exit_price": 24.734800939170526, "qty": 77.5277821, "fee": 3.736436025564888, "size": 1818.801768066, "PNL": 95.09605340732296, "PNL_percentage": 5.228500162964002, "holding_period": 46920.0, "opened_at": 1752850800000.0, "closed_at": 1752897720000.0}, {"id": "9acf0d72-993b-4b6e-af02-490affff3eb7", "strategy_name": "AlligatorV2", "symbol": "ETC-USDT", "exchange": "Bybit Spot", "type": "long", "entry_price": 23.34, "exit_price": 23.88893781260757, "qty": 181.75793111, "fee": 8.5842340253424, "size": 4242.2301121074, "PNL": 91.18956710225825, "PNL_percentage": 2.149566730055534, "holding_period": 16080.0, "opened_at": 1754762400000.0, "closed_at": 1754778480000.0}, {"id": "a862670b-0973-4c31-bf9e-a3d84fd780ff", "strategy_name": "AlligatorV2", "symbol": "ETC-USDT", "exchange": "Bybit Spot", "type": "long", "entry_price": 23.59, "exit_price": 22.685098692000448, "qty": 154.69992487, "fee": 7.158754291004305, "size": 3649.3712276833, "PNL": -147.14691865329968, "PNL_percentage": -4.032117027094328, "holding_period": 14580.0, "opened_at": 1754798400000.0, "closed_at": 1754812980000.0}], "considering_timeframes": ["1m", "4h", "1h"]}